easyjsonpy/__init__.py
easyjsonpy/config_loader.py
easyjsonpy/exceptions.py
easyjsonpy/lang_loader.py
easyjsonpy-1.0.0.dist-info/METADATA
easyjsonpy-1.0.0.dist-info/WHEEL
easyjsonpy-1.0.0.dist-info/top_level.txt
easyjsonpy-1.0.0.dist-info/RECORD
