Metadata-Version: 2.1
Name: easyjsonpy
Version: 1.0.0
Summary: Python library that allows you to easily load languages and settings ​​into your project using JSON files
Author-email: "Pedro Agustin Vega (wrrulos)" <vegapedroagustin2004@gmail.com>
License: MIT License
Project-URL: homepage, https://github.com/wrrulos/easyjsonpy
Project-URL: documentation, https://github.com/wrrulos/easyjsonpy
Project-URL: repository, https://github.com/wrrulos/easyjsonpy
Keywords: language,settings,python,json
Classifier: Programming Language :: Python :: 3
Classifier: License :: OSI Approved :: MIT License
Classifier: Operating System :: OS Independent
Requires-Python: >=3.6
Requires-Dist: aiofiles
